malcore_playbook
test_plugins
