Metadata-Version: 2.1
Name: malcore-playbook
Version: 1.0.1.1
Summary: Malcore Playbook automates malware analysis, malware triaging, and analyst workflows using modular recipes and DSL scripting
Home-page: https://github.com/PenetrumLLC/malcore-playbook
Author: Thomas Perkins
Author-email: penetrumcorp@gmail.com
License-File: LICENSE.md
License-File: NOTICE.md
Requires-Dist: requests
